gatetools/__init__.py
gatetools/affine_transform.py
gatetools/bounding_box.py
gatetools/dvh.py
gatetools/gamma_index.py
gatetools/gate_helpers.py
gatetools/gauss_filter.py
gatetools/hausdorff.py
gatetools/image_arithm.py
gatetools/image_convert.py
gatetools/image_crop.py
gatetools/image_resize.py
gatetools/image_statistics.py
gatetools/image_to_dicom_rt_struct.py
gatetools/image_uncertainty.py
gatetools/logging_conf.py
gatetools/merge_root.py
gatetools/morpho_math.py
gatetools/pbs_plan_file.py
gatetools/pet_helpers.py
gatetools/pet_helpers_with_debug.py
gatetools/roi_utils.py
gatetools/write_dicom.py
gatetools/bin/gt_affine_transform.py
gatetools/bin/gt_dicom_info.py
gatetools/bin/gt_dicom_rt_pbs2gate.py
gatetools/bin/gt_dicom_rt_struct_to_image.py
gatetools/bin/gt_digi_mac_converter.py
gatetools/bin/gt_dvh.py
gatetools/bin/gt_gamma_index.py
gatetools/bin/gt_gate_info.py
gatetools/bin/gt_hausdorff.py
gatetools/bin/gt_image_arithm.py
gatetools/bin/gt_image_convert.py
gatetools/bin/gt_image_crop.py
gatetools/bin/gt_image_gauss.py
gatetools/bin/gt_image_resize.py
gatetools/bin/gt_image_statistics.py
gatetools/bin/gt_image_to_dicom_rt_struct.py
gatetools/bin/gt_image_uncertainty.py
gatetools/bin/gt_merge_root.py
gatetools/bin/gt_morpho_math.py
gatetools/bin/gt_pet_necr.py
gatetools/bin/gt_phsp_compare.py
gatetools/bin/gt_phsp_convert.py
gatetools/bin/gt_phsp_info.py
gatetools/bin/gt_phsp_merge.py
gatetools/bin/gt_phsp_peaks.py
gatetools/bin/gt_phsp_plot.py
gatetools/bin/gt_write_dicom.py
gatetools/clustertools/__init__.py
gatetools/clustertools/computeElapsedTime.py
gatetools/clustertools/example_opengate_run.py
gatetools/clustertools/gate_common.sh
gatetools/clustertools/gate_job_ccin2p3.job
gatetools/clustertools/gate_job_ccin2p3.slurm
gatetools/clustertools/gate_job_cluster.job
gatetools/clustertools/gate_job_idris.slurm
gatetools/clustertools/gate_power_merge.sh
gatetools/clustertools/gate_split_and_run.py
gatetools/clustertools/mergeDoseByRegions.sh
gatetools-0.12.7.dist-info/licenses/AUTHORS
gatetools-0.12.7.dist-info/licenses/LICENSE.md
gatetools-0.12.7.dist-info/METADATA
gatetools-0.12.7.dist-info/WHEEL
gatetools-0.12.7.dist-info/entry_points.txt
gatetools-0.12.7.dist-info/top_level.txt
gatetools-0.12.7.dist-info/RECORD
