Metadata-Version: 2.4
Name: gatetools
Version: 0.12.7
Summary: Python tools for GATE, see https://github.com/OpenGATE/Gate
Author-email: Opengate collaboration <david.sarrut@creatis.insa-lyon.fr>
License:                    GNU LESSER GENERAL PUBLIC LICENSE
Classifier: Programming Language :: Python
Classifier: Programming Language :: Python :: 3.9
Classifier: Programming Language :: Python :: 3.10
Classifier: Programming Language :: Python :: 3.11
Classifier: Programming Language :: Python :: 3.12
Classifier: Programming Language :: Python :: Implementation :: PyPy
Classifier: Operating System :: OS Independent
Requires-Python: >=3.7
License-File: LICENSE.md
License-File: AUTHORS
Requires-Dist: matplotlib
Requires-Dist: click
Requires-Dist: numpy
Requires-Dist: scipy
Requires-Dist: pydicom
Requires-Dist: tqdm
Requires-Dist: colored
Requires-Dist: itk>=5.2.0
Requires-Dist: uproot
Requires-Dist: wget
Requires-Dist: python-box
Requires-Dist: lz4
Requires-Dist: colorama
Requires-Dist: xxhash
Dynamic: license-file
